{"nodes": [{"id": "main", "label": "Main.tsx", "file_type": "code", "source_file": "systems/pinboard/demo/src/Main.tsx", "source_location": "L1"}, {"id": "main_main", "label": "Main()", "file_type": "code", "source_file": "systems/pinboard/demo/src/Main.tsx", "source_location": "L11"}], "edges": [{"source": "main", "target": "remotion", "relation": "imports_from", "confidence": "EXTRACTED", "source_file": "systems/pinboard/demo/src/Main.tsx", "source_location": "L1", "weight": 1.0}, {"source": "main", "target": "titlescene", "relation": "imports_from", "confidence": "EXTRACTED", "source_file": "systems/pinboard/demo/src/Main.tsx", "source_location": "L2", "weight": 1.0}, {"source": "main", "target": "uploadscene", "relation": "imports_from", "confidence": "EXTRACTED", "source_file": "systems/pinboard/demo/src/Main.tsx", "source_location": "L3", "weight": 1.0}, {"source": "main", "target": "taggingscene", "relation": "imports_from", "confidence": "EXTRACTED", "source_file": "systems/pinboard/demo/src/Main.tsx", "source_location": "L4", "weight": 1.0}, {"source": "main", "target": "multimodelscene", "relation": "imports_from", "confidence": "EXTRACTED", "source_file": "systems/pinboard/demo/src/Main.tsx", "source_location": "L5", "weight": 1.0}, {"source": "main", "target": "generationscene", "relation": "imports_from", "confidence": "EXTRACTED", "source_file": "systems/pinboard/demo/src/Main.tsx", "source_location": "L6", "weight": 1.0}, {"source": "main", "target": "historyscene", "relation": "imports_from", "confidence": "EXTRACTED", "source_file": "systems/pinboard/demo/src/Main.tsx", "source_location": "L7", "weight": 1.0}, {"source": "main", "target": "closingscene", "relation": "imports_from", "confidence": "EXTRACTED", "source_file": "systems/pinboard/demo/src/Main.tsx", "source_location": "L8", "weight": 1.0}, {"source": "main", "target": "theme", "relation": "imports_from", "confidence": "EXTRACTED", "source_file": "systems/pinboard/demo/src/Main.tsx", "source_location": "L9", "weight": 1.0}, {"source": "main", "target": "main_main", "relation": "contains", "confidence": "EXTRACTED", "source_file": "systems/pinboard/demo/src/Main.tsx", "source_location": "L11", "weight": 1.0}]}